fds/__init__.py
fds/sdk/__init__.py
fds/sdk/FactSetPortfolioOptimizer/__init__.py
fds/sdk/FactSetPortfolioOptimizer/api_client.py
fds/sdk/FactSetPortfolioOptimizer/configuration.py
fds/sdk/FactSetPortfolioOptimizer/exceptions.py
fds/sdk/FactSetPortfolioOptimizer/model_utils.py
fds/sdk/FactSetPortfolioOptimizer/rest.py
fds/sdk/FactSetPortfolioOptimizer/api/__init__.py
fds/sdk/FactSetPortfolioOptimizer/api/accounts_api.py
fds/sdk/FactSetPortfolioOptimizer/api/currencies_api.py
fds/sdk/FactSetPortfolioOptimizer/api/fpo_optimizer_api.py
fds/sdk/FactSetPortfolioOptimizer/api/strategy_documents_api.py
fds/sdk/FactSetPortfolioOptimizer/apis/__init__.py
fds/sdk/FactSetPortfolioOptimizer/model/__init__.py
fds/sdk/FactSetPortfolioOptimizer/model/account_directories.py
fds/sdk/FactSetPortfolioOptimizer/model/account_directories_root.py
fds/sdk/FactSetPortfolioOptimizer/model/calculation_info.py
fds/sdk/FactSetPortfolioOptimizer/model/calculation_info_root.py
fds/sdk/FactSetPortfolioOptimizer/model/client_error_response.py
fds/sdk/FactSetPortfolioOptimizer/model/currency.py
fds/sdk/FactSetPortfolioOptimizer/model/currency_root.py
fds/sdk/FactSetPortfolioOptimizer/model/document_directories.py
fds/sdk/FactSetPortfolioOptimizer/model/document_directories_root.py
fds/sdk/FactSetPortfolioOptimizer/model/error.py
fds/sdk/FactSetPortfolioOptimizer/model/error_source.py
fds/sdk/FactSetPortfolioOptimizer/model/fpo_account.py
fds/sdk/FactSetPortfolioOptimizer/model/fpo_optimization_parameters.py
fds/sdk/FactSetPortfolioOptimizer/model/fpo_optimization_parameters_root.py
fds/sdk/FactSetPortfolioOptimizer/model/object_root.py
fds/sdk/FactSetPortfolioOptimizer/model/optimal_portfolio.py
fds/sdk/FactSetPortfolioOptimizer/model/optimization.py
fds/sdk/FactSetPortfolioOptimizer/model/optimizer_account_overrides.py
fds/sdk/FactSetPortfolioOptimizer/model/optimizer_optimal_holdings.py
fds/sdk/FactSetPortfolioOptimizer/model/optimizer_output_types.py
fds.sdk.FactSetPortfolioOptimizer-0.21.14.dist-info/LICENSE
fds.sdk.FactSetPortfolioOptimizer-0.21.14.dist-info/METADATA
fds.sdk.FactSetPortfolioOptimizer-0.21.14.dist-info/WHEEL
fds.sdk.FactSetPortfolioOptimizer-0.21.14.dist-info/top_level.txt
fds.sdk.FactSetPortfolioOptimizer-0.21.14.dist-info/RECORD
